baipw/__init__.py
baipw/exceptions.py
baipw/middleware.py
baipw/response.py
baipw/utils.py
django_basic_auth_ip_whitelist-0.6.0.dist-info/LICENSE
django_basic_auth_ip_whitelist-0.6.0.dist-info/METADATA
django_basic_auth_ip_whitelist-0.6.0.dist-info/WHEEL
django_basic_auth_ip_whitelist-0.6.0.dist-info/top_level.txt
django_basic_auth_ip_whitelist-0.6.0.dist-info/RECORD
