Metadata-Version: 2.1
Name: django-basic-auth-ip-whitelist
Version: 0.6.0
Summary: Hide your Django site behind basic authentication mechanism with IP whitelisting support.
Home-page: https://github.com/torchbox/django-basic-auth-ip-whitelist
Author: Torchbox
Author-email: hello@torchbox.com
License: BSD 3-Clause License
Keywords: django,basic,authentication,auth,ip,whitelist,whitelisting,http
Classifier: Development Status :: 5 - Production/Stable
Classifier: License :: OSI Approved
Classifier: License :: OSI Approved :: BSD License
Classifier: Programming Language :: Python :: 3.4
Classifier: Programming Language :: Python :: 3.5
Classifier: Programming Language :: Python :: 3.6
Classifier: Programming Language :: Python :: 3.7
Classifier: Programming Language :: Python :: 3.8
Classifier: Programming Language :: Python :: 3.9
Classifier: Programming Language :: Python :: 3.10
Classifier: Programming Language :: Python :: 3.11
Classifier: Programming Language :: Python :: 3.12
Classifier: Topic :: Internet :: WWW/HTTP
Classifier: Framework :: Django
Classifier: Framework :: Django :: 1.8
Classifier: Framework :: Django :: 1.9
Classifier: Framework :: Django :: 1.10
Classifier: Framework :: Django :: 1.11
Classifier: Framework :: Django :: 2.0
Classifier: Framework :: Django :: 2.1
Classifier: Framework :: Django :: 2.2
Classifier: Framework :: Django :: 3.0
Classifier: Framework :: Django :: 3.1
Classifier: Framework :: Django :: 4.0
Classifier: Framework :: Django :: 4.1
Classifier: Framework :: Django :: 4.2
Classifier: Framework :: Django :: 5.0
Requires-Python: >=3.4
License-File: LICENSE
Requires-Dist: Django <6,>=1.8
Provides-Extra: lint
Requires-Dist: isort ==5.13.2 ; extra == 'lint'
Requires-Dist: flake8 ==7.0.0 ; extra == 'lint'
Requires-Dist: black ==24.4.2 ; extra == 'lint'
